django_angular_template_i18n_lint.py
setup.cfg
setup.py
django_angular_template_i18n_lint.egg-info/PKG-INFO
django_angular_template_i18n_lint.egg-info/SOURCES.txt
django_angular_template_i18n_lint.egg-info/dependency_links.txt
django_angular_template_i18n_lint.egg-info/entry_points.txt
django_angular_template_i18n_lint.egg-info/top_level.txt