Metadata-Version: 1.1
Name: django-angular-template-i18n-lint
Version: 0.1
Summary: Lint tool to find non-trans/blocktrans/|translate text in django/angular templates
Home-page: https://github.com/ArabellaTech/django-angular-template-i18n-lint/
Author: Arabel.la
Author-email: jacek@arabel.la
License: GPLv3+
Platform: UNKNOWN
Classifier: Development Status :: 5 - Production/Stable
Classifier: License :: OSI Approved :: GNU General Public License v3 or later (GPLv3+)
Classifier: License :: OSI Approved :: BSD License
Classifier: Environment :: Console
Classifier: Framework :: Django
Classifier: Intended Audience :: Developers
Classifier: Operating System :: OS Independent
Classifier: Programming Language :: Python
Classifier: Programming Language :: Python :: 2
Classifier: Programming Language :: Python :: 2.7
Classifier: Programming Language :: Python :: 3
Classifier: Programming Language :: Python :: 3.3
